socs/__init__.py
socs/_version.py
socs/plugin.py
socs/snmp.py
socs/tcp.py
socs/util.py
socs/Lakeshore/Lakeshore240.py
socs/Lakeshore/Lakeshore336.py
socs/Lakeshore/Lakeshore370.py
socs/Lakeshore/Lakeshore372.py
socs/Lakeshore/Lakeshore425.py
socs/Lakeshore/__init__.py
socs/agents/__init__.py
socs/agents/ocs_plugin_so.py
socs/agents/acu/__init__.py
socs/agents/acu/agent.py
socs/agents/acu/avoidance.py
socs/agents/acu/drivers.py
socs/agents/acu/exercisor.py
socs/agents/acu/hvac.py
socs/agents/acu/hwp_iface.py
socs/agents/bluefors/__init__.py
socs/agents/bluefors/agent.py
socs/agents/cryomech_cpa/__init__.py
socs/agents/cryomech_cpa/agent.py
socs/agents/cryomech_cpa/drivers.py
socs/agents/devantech_dS378/__init__.py
socs/agents/devantech_dS378/agent.py
socs/agents/devantech_dS378/drivers.py
socs/agents/fts_aerotech/__init__.py
socs/agents/fts_aerotech/agent.py
socs/agents/generator/__init__.py
socs/agents/generator/agent.py
socs/agents/generator/sample_configs/Alarms.yaml
socs/agents/generator/sample_configs/Engine_Data.yaml
socs/agents/hi6200/__init__.py
socs/agents/hi6200/agent.py
socs/agents/hi6200/drivers.py
socs/agents/holo_fpga/__init__.py
socs/agents/holo_fpga/agent.py
socs/agents/holo_synth/__init__.py
socs/agents/holo_synth/agent.py
socs/agents/http_camera/__init__.py
socs/agents/http_camera/agent.py
socs/agents/http_camera/sample_config.yaml
socs/agents/hwp_encoder/__init__.py
socs/agents/hwp_encoder/agent.py
socs/agents/hwp_gripper/__init__.py
socs/agents/hwp_gripper/agent.py
socs/agents/hwp_gripper/drivers/__init__.py
socs/agents/hwp_gripper/drivers/gripper_client.py
socs/agents/hwp_pcu/__init__.py
socs/agents/hwp_pcu/agent.py
socs/agents/hwp_pcu/drivers/__init__.py
socs/agents/hwp_pcu/drivers/hwp_pcu.py
socs/agents/hwp_picoscope/__init__.py
socs/agents/hwp_picoscope/agent.py
socs/agents/hwp_picoscope/drivers/__init__.py
socs/agents/hwp_picoscope/drivers/class_ps3000a.py
socs/agents/hwp_pid/__init__.py
socs/agents/hwp_pid/agent.py
socs-0.5.7.dist-info/METADATA
socs-0.5.7.dist-info/WHEEL
socs-0.5.7.dist-info/entry_points.txt
socs-0.5.7.dist-info/licenses/LICENSE.txt
socs-0.5.7.dist-info/RECORD
