Metadata-Version: 2.4
Name: socs
Version: 0.5.7
Summary: Simons Observatory Control System
Project-URL: Bug Tracker, https://github.com/simonsobs/ocs/issues
Project-URL: Documentation, https://ocs.readthedocs.io/
Project-URL: Homepage, https://github.com/simonsobs/socs
Project-URL: Source Code, https://github.com/simonsobs/ocs
License-File: LICENSE.txt
Classifier: Framework :: Twisted
Classifier: Intended Audience :: Science/Research
Classifier: License :: OSI Approved :: BSD License
Classifier: Programming Language :: Python :: 3
Classifier: Programming Language :: Python :: 3.7
Classifier: Programming Language :: Python :: 3.8
Classifier: Programming Language :: Python :: 3.9
Classifier: Programming Language :: Python :: 3.10
Classifier: Programming Language :: Python :: 3.11
Classifier: Topic :: Scientific/Engineering :: Astronomy
Requires-Python: >=3.7
Requires-Dist: autobahn[serialization]
Requires-Dist: numpy
Requires-Dist: ocs
Requires-Dist: pyasn1==0.4.8
Requires-Dist: pymodbustcp
Requires-Dist: pyserial
Requires-Dist: pysmi
Requires-Dist: pysnmp==4.4.12
Requires-Dist: pyyaml
Requires-Dist: requests
Requires-Dist: sqlalchemy>=1.4
Requires-Dist: tqdm
Requires-Dist: twisted
Provides-Extra: acu
Requires-Dist: pixell; extra == 'acu'
Requires-Dist: so3g; extra == 'acu'
Provides-Extra: all
Requires-Dist: imutils; extra == 'all'
Requires-Dist: labjack-ljm; extra == 'all'
Requires-Dist: numexpr; extra == 'all'
Requires-Dist: opencv-python; extra == 'all'
Requires-Dist: pandas; extra == 'all'
Requires-Dist: pfeiffer-vacuum-protocol==0.4; extra == 'all'
Requires-Dist: pixell; extra == 'all'
Requires-Dist: pyepics; extra == 'all'
Requires-Dist: scipy; extra == 'all'
Requires-Dist: so3g; extra == 'all'
Provides-Extra: camera
Requires-Dist: imutils; extra == 'camera'
Requires-Dist: opencv-python; extra == 'camera'
Provides-Extra: labjack
Requires-Dist: labjack-ljm; extra == 'labjack'
Requires-Dist: numexpr; extra == 'labjack'
Requires-Dist: scipy; extra == 'labjack'
Provides-Extra: magpie
Requires-Dist: pandas; extra == 'magpie'
Requires-Dist: scipy; extra == 'magpie'
Requires-Dist: so3g; extra == 'magpie'
Provides-Extra: pfeiffer
Requires-Dist: pfeiffer-vacuum-protocol==0.4; extra == 'pfeiffer'
Provides-Extra: pysmurf
Requires-Dist: pyepics; extra == 'pysmurf'
Provides-Extra: smurf-sim
Requires-Dist: so3g; extra == 'smurf-sim'
Provides-Extra: timing-master
Requires-Dist: pyepics; extra == 'timing-master'
